jax_xc-0.0.11.dist-info/METADATA
jax_xc-0.0.11.dist-info/RECORD
jax_xc-0.0.11.dist-info/WHEEL
jax_xc/__init__.py
jax_xc/experimental.py
jax_xc/functionals.py
jax_xc/impl/__init__.py
jax_xc/impl/gga_c_acgga.py
jax_xc/impl/gga_c_acggap.py
jax_xc/impl/gga_c_am05.py
jax_xc/impl/gga_c_bmk.py
jax_xc/impl/gga_c_ccdf.py
jax_xc/impl/gga_c_chachiyo.py
jax_xc/impl/gga_c_cs1.py
jax_xc/impl/gga_c_ft97.py
jax_xc/impl/gga_c_gapc.py
jax_xc/impl/gga_c_gaploc.py
jax_xc/impl/gga_c_hcth_a.py
jax_xc/impl/gga_c_lm.py
jax_xc/impl/gga_c_lyp.py
jax_xc/impl/gga_c_lypr.py
jax_xc/impl/gga_c_op_b88.py
jax_xc/impl/gga_c_op_g96.py
jax_xc/impl/gga_c_op_pbe.py
jax_xc/impl/gga_c_op_pw91.py
jax_xc/impl/gga_c_op_xalpha.py
jax_xc/impl/gga_c_optc.py
jax_xc/impl/gga_c_p86.py
jax_xc/impl/gga_c_p86vwn.py
jax_xc/impl/gga_c_pbe.py
jax_xc/impl/gga_c_pbe_vwn.py
jax_xc/impl/gga_c_pbeloc.py
jax_xc/impl/gga_c_pw91.py
jax_xc/impl/gga_c_q2d.py
jax_xc/impl/gga_c_regtpss.py
jax_xc/impl/gga_c_revtca.py
jax_xc/impl/gga_c_scan_e0.py
jax_xc/impl/gga_c_sg4.py
jax_xc/impl/gga_c_sogga11.py
jax_xc/impl/gga_c_tca.py
jax_xc/impl/gga_c_w94.py
jax_xc/impl/gga_c_wi.py
jax_xc/impl/gga_c_wl.py
jax_xc/impl/gga_c_zpbeint.py
jax_xc/impl/gga_c_zvpbeint.py
jax_xc/impl/gga_c_zvpbeloc.py
jax_xc/impl/gga_k_apbe.py
jax_xc/impl/gga_k_apbeint.py
jax_xc/impl/gga_k_dk.py
jax_xc/impl/gga_k_exp4.py
jax_xc/impl/gga_k_lc94.py
jax_xc/impl/gga_k_lgap.py
jax_xc/impl/gga_k_lgap_ge.py
jax_xc/impl/gga_k_lkt.py
jax_xc/impl/gga_k_llp.py
jax_xc/impl/gga_k_meyer.py
jax_xc/impl/gga_k_mpbe.py
jax_xc/impl/gga_k_ol1.py
jax_xc/impl/gga_k_ol2.py
jax_xc/impl/gga_k_pearson.py
jax_xc/impl/gga_k_pg.py
jax_xc/impl/gga_k_pw86.py
jax_xc/impl/gga_k_rational_p.py
jax_xc/impl/gga_k_tflw.py
jax_xc/impl/gga_k_thakkar.py
jax_xc/impl/gga_k_vt84f.py
jax_xc/impl/gga_x_2d_b86.py
jax_xc/impl/gga_x_2d_b86_mgc.py
jax_xc/impl/gga_x_2d_b88.py
jax_xc/impl/gga_x_2d_pbe.py
jax_xc/impl/gga_x_airy.py
jax_xc/impl/gga_x_ak13.py
jax_xc/impl/gga_x_am05.py
jax_xc/impl/gga_x_b86.py
jax_xc/impl/gga_x_b88.py
jax_xc/impl/gga_x_bayesian.py
jax_xc/impl/gga_x_beefvdw.py
