Metadata-Version: 2.1
Name: jax_xc
Version: 0.0.11
Author: Kunhao Zheng, Min Lin
Author-email: zhengkh@sea.com, linmin@sea.com
Classifier: Topic :: Scientific/Engineering :: Chemistry
Classifier: Programming Language :: Python :: 3
Requires-Python: >=3.9
Requires-Dist: jax
Requires-Dist: numpy
Requires-Dist: tensorflow-probability
Requires-Dist: autofd
